{"assets":{"218C388A157E683BB1CD1B62B2692166":{"type":"texture","index":7,"assetRequest":{"type":"slide","state":"contents","slide":"none"},"url":{"native":"assets\/6BCCB8FB-3FFF-413F-9704-86E133D1348F.pdf"},"width":1024,"height":768},"0A4CBFA773B53791C1FFEC30F9CAE04B":{"type":"texture","index":4,"assetRequest":{"type":"slide","state":"contents","slide":"none"},"url":{"native":"assets\/6BCCB8FB-3FFF-413F-9704-86E133D1348F.pdf"},"width":175,"height":276},"08EB21BA8CB7EFB598C0A6F99F019120":{"type":"texture","index":5,"assetRequest":{"type":"slide","state":"contents","slide":"none"},"url":{"native":"assets\/6BCCB8FB-3FFF-413F-9704-86E133D1348F.pdf"},"width":120,"height":158},"Audio Recording.m4a-0.0000-126.7717":{"type":"audio","index":0,"assetRequest":{"type":"slide","state":"contents","slide":"none"},"url":{"web":"assets\/Audio Recording.m4a-0.0000-126.7717.m4a","native":"assets\/Audio Recording.m4a-0.0000-126.7717.m4a"},"width":0,"height":0},"DB8451458D98EFA7506DBEBC2B1323F0":{"type":"texture","index":0,"assetRequest":{"type":"slide","state":"contents","slide":"none"},"url":{"native":"assets\/6BCCB8FB-3FFF-413F-9704-86E133D1348F.pdf"},"width":1024,"height":768},"89124461825D969D2B5FF2028E29CF42":{"type":"texture","index":2,"assetRequest":{"type":"slide","state":"contents","slide":"none"},"url":{"native":"assets\/6BCCB8FB-3FFF-413F-9704-86E133D1348F.pdf"},"width":604,"height":333},"588FD90B0ECC9E63AEAA605BF27CA224":{"type":"texture","index":1,"assetRequest":{"type":"slide","state":"contents","slide":"none"},"url":{"native":"assets\/6BCCB8FB-3FFF-413F-9704-86E133D1348F.pdf"},"width":604,"height":269},"5C896C21DC769790EFC52CDFA9579CF0":{"type":"texture","index":3,"assetRequest":{"type":"slide","state":"contents","slide":"none"},"url":{"native":"assets\/6BCCB8FB-3FFF-413F-9704-86E133D1348F.pdf"},"width":297,"height":227},"730F45CA9B52757583F432DB4F57BC3E":{"type":"texture","index":6,"assetRequest":{"type":"slide","state":"contents","slide":"none"},"url":{"native":"assets\/6BCCB8FB-3FFF-413F-9704-86E133D1348F.pdf"},"width":1024,"height":768}},"events":[{"effects":[{"beginTime":0,"effects":[{"beginTime":0,"effects":[],"movie":{"startTime":0,"volume":1,"endTime":126.77166666666666,"isStreaming":false,"isAudioOnly":true,"asset":"Audio Recording.m4a-0.0000-126.7717"},"duration":0,"type":"buildIn","attributes":{"direction":0},"name":"renderMovie","objectID":"D22DD056-2608-469E-9BB9-17E9A327A4FD"}],"duration":0.5,"type":"buildIn","attributes":{"direction":0},"name":"apple:audio-start","objectID":"D22DD056-2608-469E-9BB9-17E9A327A4FD"}],"automaticPlay":true,"hyperlinks":[],"accessibility":[{"text":"pasted-image.tiff","targetRectangle":{"y":385.57037353515625,"x":371.70663452148438,"width":600.78125,"height":330.42962646484375}},{"text":"pasted-image.tiff","targetRectangle":{"y":613.63971914356614,"x":-0.80919802188873291,"width":117.125,"height":155.2908340327723}},{"text":"Newtonian Gravity ","targetRectangle":{"y":111.540358543396,"x":34.578115463256779,"width":296.97500000000008,"height":48}},{"text":"to ","targetRectangle":{"y":159.540358543396,"x":162.29311546325684,"width":41.545000000000016,"height":48}},{"text":"Einstein’s ","targetRectangle":{"y":207.540358543396,"x":107.20311546325684,"width":151.72500000000002,"height":48}},{"text":"General Relativity","targetRectangle":{"y":255.540358543396,"x":42.383115463256786,"width":272.26500000000004,"height":48}},{"text":"(1919)","targetRectangle":{"y":303.540358543396,"x":133.01561546325684,"width":91,"height":48}},{"text":"pasted-image.tiff","targetRectangle":{"y":99.118499755859375,"x":371.70662294261092,"width":600.79682721261634,"height":266.83578205496815}},{"text":"Classical ","targetRectangle":{"y":406.78515434265137,"x":112.10311546325684,"width":141.92499999999998,"height":48}},{"text":"Mechanics","targetRectangle":{"y":454.78515434265137,"x":96.195615463256829,"width":164.63999999999999,"height":48}},{"text":"to ","targetRectangle":{"y":502.78515434265137,"x":162.29311546325684,"width":41.545000000000016,"height":48}},{"text":"Quantum ","targetRectangle":{"y":550.78515434265137,"x":104.91061546325685,"width":156.31000000000003,"height":48}},{"text":"Mechanics ","targetRectangle":{"y":598.78515434265137,"x":96.195615463256843,"width":173.74000000000001,"height":48}},{"text":"(1905)","targetRectangle":{"y":646.78515434265137,"x":133.01561546325684,"width":91,"height":48}}],"baseLayer":{"animations":[],"initialState":{"affineTransform":[1,0,0,1,0,0],"masksToBounds":false,"rotation":0,"scale":1,"position":{"pointX":512,"pointY":384},"width":1024,"sublayerTransform":[1,0,0,0,0,1,0,0,0,0,1,0,0,0,0,1],"contentsRect":{"y":0,"x":0,"width":1,"height":1},"opacity":1,"edgeAntialiasingMask":251658240,"height":768,"hidden":false,"anchorPoint":{"pointX":0.5,"pointY":0.5}},"layers":[{"animations":[],"initialState":{"affineTransform":[1,0,0,1,0,0],"masksToBounds":false,"rotation":0,"scale":1,"position":{"pointX":512,"pointY":384},"width":1024,"sublayerTransform":[1,0,0,0,0,1,0,0,0,0,1,0,0,0,0,1],"contentsRect":{"y":0,"x":0,"width":1,"height":1},"opacity":1,"edgeAntialiasingMask":251658240,"height":768,"hidden":false,"anchorPoint":{"pointX":0.5,"pointY":0.5}},"layers":[{"animations":[],"initialState":{"affineTransform":[1,0,0,1,0,0],"masksToBounds":false,"rotation":0,"scale":1,"position":{"pointX":512,"pointY":384},"width":1024,"sublayerTransform":[1,0,0,0,0,1,0,0,0,0,1,0,0,0,0,1],"contentsRect":{"y":0,"x":0,"width":1,"height":1},"opacity":1,"edgeAntialiasingMask":251658240,"height":768,"hidden":false,"anchorPoint":{"pointX":0.5,"pointY":0.5}},"layers":[{"animations":[],"layers":[],"texturedRectangle":{"isBackgroundTexture":true,"singleTextureOpacity":1,"textureType":1,"textBaseline":0,"textXHeight":0,"isVerticalText":false},"initialState":{"affineTransform":[1,0,0,1,0,0],"masksToBounds":false,"rotation":0,"scale":1,"position":{"pointX":512,"pointY":384},"width":1024,"sublayerTransform":[1,0,0,0,0,1,0,0,0,0,1,0,0,0,0,1],"contentsRect":{"y":0,"x":0,"width":1,"height":1},"opacity":1,"edgeAntialiasingMask":0,"height":768,"hidden":false,"anchorPoint":{"pointX":0.5,"pointY":0.5}},"texture":"DB8451458D98EFA7506DBEBC2B1323F0"}]}]},{"animations":[],"initialState":{"affineTransform":[1,0,0,1,0,0],"masksToBounds":false,"rotation":0,"scale":1,"position":{"pointX":512,"pointY":384},"width":1024,"sublayerTransform":[1,0,0,0,0,1,0,0,0,0,1,0,0,0,0,1],"contentsRect":{"y":0,"x":0,"width":1,"height":1},"opacity":1,"edgeAntialiasingMask":251658240,"height":768,"hidden":false,"anchorPoint":{"pointX":0.5,"pointY":0.5}},"layers":[{"animations":[],"initialState":{"affineTransform":[1,0,0,1,0,0],"masksToBounds":false,"rotation":0,"scale":1,"position":{"pointX":673.70662294261092,"pointY":233.61849975585938},"width":604,"sublayerTransform":[1,0,0,0,0,1,0,0,0,0,1,0,0,0,0,1],"contentsRect":{"y":0,"x":0,"width":1,"height":1},"opacity":1,"edgeAntialiasingMask":251658240,"height":269,"hidden":false,"anchorPoint":{"pointX":0.5,"pointY":0.5}},"layers":[{"animations":[],"layers":[],"texturedRectangle":{"isBackgroundTexture":true,"singleTextureOpacity":1,"textureType":5,"textBaseline":0,"textXHeight":0,"isVerticalText":false},"initialState":{"affineTransform":[1,0,0,1,0,0],"masksToBounds":false,"rotation":0,"scale":1,"position":{"pointX":300.29337705738908,"pointY":133.38150024414062},"width":604,"sublayerTransform":[1,0,0,0,0,1,0,0,0,0,1,0,0,0,0,1],"contentsRect":{"y":0,"x":0,"width":1,"height":1},"opacity":1,"edgeAntialiasingMask":0,"height":269,"hidden":false,"anchorPoint":{"pointX":0.5,"pointY":0.5}},"texture":"588FD90B0ECC9E63AEAA605BF27CA224"}]}]},{"animations":[],"initialState":{"affineTransform":[1,0,0,1,0,0],"masksToBounds":false,"rotation":0,"scale":1,"position":{"pointX":512,"pointY":384},"width":1024,"sublayerTransform":[1,0,0,0,0,1,0,0,0,0,1,0,0,0,0,1],"contentsRect":{"y":0,"x":0,"width":1,"height":1},"opacity":1,"edgeAntialiasingMask":251658240,"height":768,"hidden":false,"anchorPoint":{"pointX":0.5,"pointY":0.5}},"layers":[{"animations":[],"initialState":{"affineTransform":[1,0,0,1,0,0],"masksToBounds":false,"rotation":0,"scale":1,"position":{"pointX":673.70663452148438,"pointY":552.07037353515625},"width":604,"sublayerTransform":[1,0,0,0,0,1,0,0,0,0,1,0,0,0,0,1],"contentsRect":{"y":0,"x":0,"width":1,"height":1},"opacity":1,"edgeAntialiasingMask":251658240,"height":333,"hidden":false,"anchorPoint":{"pointX":0.5,"pointY":0.5}},"layers":[{"animations":[],"layers":[],"texturedRectangle":{"isBackgroundTexture":true,"singleTextureOpacity":1,"textureType":5,"textBaseline":0,"textXHeight":0,"isVerticalText":false},"initialState":{"affineTransform":[1,0,0,1,0,0],"masksToBounds":false,"rotation":0,"scale":1,"position":{"pointX":300.29336547851562,"pointY":164.92962646484375},"width":604,"sublayerTransform":[1,0,0,0,0,1,0,0,0,0,1,0,0,0,0,1],"contentsRect":{"y":0,"x":0,"width":1,"height":1},"opacity":1,"edgeAntialiasingMask":0,"height":333,"hidden":false,"anchorPoint":{"pointX":0.5,"pointY":0.5}},"texture":"89124461825D969D2B5FF2028E29CF42"}]}]},{"animations":[],"initialState":{"affineTransform":[1,0,0,1,0,0],"masksToBounds":false,"rotation":0,"scale":1,"position":{"pointX":512,"pointY":384},"width":1024,"sublayerTransform":[1,0,0,0,0,1,0,0,0,0,1,0,0,0,0,1],"contentsRect":{"y":0,"x":0,"width":1,"height":1},"opacity":1,"edgeAntialiasingMask":251658240,"height":768,"hidden":false,"anchorPoint":{"pointX":0.5,"pointY":0.5}},"layers":[{"animations":[],"initialState":{"affineTransform":[1,0,0,1,0,0],"masksToBounds":false,"rotation":0,"scale":1,"position":{"pointX":178.09999656677246,"pointY":221.040358543396},"width":297,"sublayerTransform":[1,0,0,0,0,1,0,0,0,0,1,0,0,0,0,1],"contentsRect":{"y":0,"x":0,"width":1,"height":1},"opacity":1,"edgeAntialiasingMask":251658240,"height":227,"hidden":false,"anchorPoint":{"pointX":0.5,"pointY":0.5}},"layers":[{"animations":[],"layers":[],"texturedRectangle":{"singleTextureOpacity":1,"textXHeight":0.071233480176211464,"textBaseline":0.96797556183936839,"isBackgroundTexture":true,"isVerticalText":false,"textColor":[0.9999966025352478,0.99999994039535522,0.99999994039535522,1],"textureType":6},"initialState":{"affineTransform":[1,0,0,1,0,0],"masksToBounds":false,"rotation":0,"scale":1,"position":{"pointX":154.90000343322754,"pointY":124.959641456604},"width":297,"sublayerTransform":[1,0,0,0,0,1,0,0,0,0,1,0,0,0,0,1],"contentsRect":{"y":0,"x":0,"width":1,"height":1},"opacity":1,"edgeAntialiasingMask":0,"height":227,"hidden":false,"anchorPoint":{"pointX":0.5,"pointY":0.5}},"texture":"5C896C21DC769790EFC52CDFA9579CF0"}]}]},{"animations":[],"initialState":{"affineTransform":[1,0,0,1,0,0],"masksToBounds":false,"rotation":0,"scale":1,"position":{"pointX":512,"pointY":384},"width":1024,"sublayerTransform":[1,0,0,0,0,1,0,0,0,0,1,0,0,0,0,1],"contentsRect":{"y":0,"x":0,"width":1,"height":1},"opacity":1,"edgeAntialiasingMask":251658240,"height":768,"hidden":false,"anchorPoint":{"pointX":0.5,"pointY":0.5}},"layers":[{"animations":[],"initialState":{"affineTransform":[1,0,0,1,0,0],"masksToBounds":false,"rotation":0,"scale":1,"position":{"pointX":117.09999656677246,"pointY":540.78515434265137},"width":175,"sublayerTransform":[1,0,0,0,0,1,0,0,0,0,1,0,0,0,0,1],"contentsRect":{"y":0,"x":0,"width":1,"height":1},"opacity":1,"edgeAntialiasingMask":251658240,"height":276,"hidden":false,"anchorPoint":{"pointX":0.5,"pointY":0.5}},"layers":[{"animations":[],"layers":[],"texturedRectangle":{"singleTextureOpacity":1,"textXHeight":0.058586956521739134,"textBaseline":0.97454800122026086,"isBackgroundTexture":true,"isVerticalText":false,"textColor":[0.9999966025352478,0.99999994039535522,0.99999994039535522,1],"textureType":6},"initialState":{"affineTransform":[1,0,0,1,0,0],"masksToBounds":false,"rotation":0,"scale":1,"position":{"pointX":154.90000343322754,"pointY":148.21484565734863},"width":175,"sublayerTransform":[1,0,0,0,0,1,0,0,0,0,1,0,0,0,0,1],"contentsRect":{"y":0,"x":0,"width":1,"height":1},"opacity":1,"edgeAntialiasingMask":0,"height":276,"hidden":false,"anchorPoint":{"pointX":0.5,"pointY":0.5}},"texture":"0A4CBFA773B53791C1FFEC30F9CAE04B"}]}]},{"animations":[],"initialState":{"affineTransform":[1,0,0,1,0,0],"masksToBounds":false,"rotation":0,"scale":1,"position":{"pointX":512,"pointY":384},"width":1024,"sublayerTransform":[1,0,0,0,0,1,0,0,0,0,1,0,0,0,0,1],"contentsRect":{"y":0,"x":0,"width":1,"height":1},"opacity":1,"edgeAntialiasingMask":251658240,"height":768,"hidden":false,"anchorPoint":{"pointX":0.5,"pointY":0.5}},"layers":[{"animations":[],"initialState":{"affineTransform":[1,0,0,1,0,0],"masksToBounds":false,"rotation":0,"scale":1,"position":{"pointX":59.190801978111267,"pointY":692.63971914356614},"width":120,"sublayerTransform":[1,0,0,0,0,1,0,0,0,0,1,0,0,0,0,1],"contentsRect":{"y":0,"x":0,"width":1,"height":1},"opacity":1,"edgeAntialiasingMask":251658240,"height":158,"hidden":false,"anchorPoint":{"pointX":0.5,"pointY":0.5}},"layers":[{"animations":[],"layers":[],"texturedRectangle":{"isBackgroundTexture":true,"singleTextureOpacity":1,"textureType":5,"textBaseline":0,"textXHeight":0,"isVerticalText":false},"initialState":{"affineTransform":[1,0,0,1,0,0],"masksToBounds":false,"rotation":0,"scale":1,"position":{"pointX":58.809198021888733,"pointY":77.36028085643386},"width":120,"sublayerTransform":[1,0,0,0,0,1,0,0,0,0,1,0,0,0,0,1],"contentsRect":{"y":0,"x":0,"width":1,"height":1},"opacity":1,"edgeAntialiasingMask":0,"height":158,"hidden":false,"anchorPoint":{"pointX":0.5,"pointY":0.5}},"texture":"08EB21BA8CB7EFB598C0A6F99F019120"}]}]}]}},{"effects":[{"beginTime":0,"baseLayer":{"animations":[],"initialState":{"affineTransform":[1,0,0,1,0,0],"masksToBounds":false,"rotation":0,"scale":1,"position":{"pointX":512,"pointY":384},"width":1024,"sublayerTransform":[1,0,0,0,0,1,0,0,0,0,1,0,0,0,0,1],"contentsRect":{"y":0,"x":0,"width":1,"height":1},"opacity":1,"edgeAntialiasingMask":251658240,"height":768,"hidden":false,"anchorPoint":{"pointX":0.5,"pointY":0.5}},"objectID":"0","layers":[{"animations":[],"initialState":{"affineTransform":[1,0,0,1,0,0],"masksToBounds":false,"rotation":0,"scale":1,"position":{"pointX":512,"pointY":384},"width":1024,"sublayerTransform":[1,0,0,0,0,1,0,0,0,0,1,-0.00049229876906403734,0,0,0,1],"contentsRect":{"y":0,"x":0,"width":1,"height":1},"opacity":1,"edgeAntialiasingMask":251658240,"height":768,"hidden":false,"anchorPoint":{"pointX":0.5,"pointY":0.5}},"layers":[{"animations":[{"timeOffset":0,"beginTime":0,"repeatCount":0,"animations":[{"timeOffset":0,"from":{"scalar":0.5},"beginTime":0,"repeatCount":0,"fillMode":"both","duration":0.22499999999999998,"autoreverses":false,"timingFunction":"EaseOut","property":"opacity","to":{"scalar":1}},{"timeOffset":0,"from":{"scalar":false},"beginTime":0,"repeatCount":0,"fillMode":"removed","property":"doubleSided","autoreverses":false,"duration":1.5,"to":{"scalar":false}},{"timeOffset":0,"timingFunctions":[{"timingFunction":"custom","timingControlPoint1y":0,"timingControlPoint2x":0.6983528733253479,"timingControlPoint1x":0.30636021494865417,"timingControlPoint2y":1},{"timingFunction":"custom","timingControlPoint1y":0,"timingControlPoint2x":0.69753515720367432,"timingControlPoint1x":0.29726776480674744,"timingControlPoint2y":1},{"timingFunction":"custom","timingControlPoint1y":0,"timingControlPoint2x":0.70256143808364868,"timingControlPoint1x":0.30822962522506714,"timingControlPoint2y":1},{"timingFunction":"custom","timingControlPoint1y":0,"timingControlPoint2x":0.69328594207763672,"timingControlPoint1x":0.29690060019493103,"timingControlPoint2y":1}],"beginTime":0,"values":[{"scalar":1.5707963267948966},{"scalar":1.6707963267948966},{"scalar":-0.10000000000000001},{"scalar":0.029999999999999999},{"scalar":-0}],"repeatCount":0,"fillMode":"removed","property":"transform.rotation.y","autoreverses":false,"duration":1.5,"keyTimes":[0,0.14999999999999999,0.55000000000000004,0.77500000000000002,1]},{"timeOffset":0,"from":{"scalar":-512},"beginTime":0,"repeatCount":0,"fillMode":"removed","property":"transform.translation.z","autoreverses":false,"duration":1.5,"to":{"scalar":-512}},{"timeOffset":0,"from":{"scalar":-512},"beginTime":0,"repeatCount":0,"fillMode":"removed","property":"anchorPointZ","autoreverses":false,"duration":1.5,"to":{"scalar":-512}}],"fillMode":"both","autoreverses":false,"duration":1.5}],"layers":[],"texturedRectangle":{"isBackgroundTexture":false,"singleTextureOpacity":1,"textureType":0,"textBaseline":0,"textXHeight":0,"isVerticalText":false},"initialState":{"affineTransform":[1,0,0,1,0,0],"masksToBounds":false,"rotation":0,"scale":1,"position":{"pointX":512,"pointY":384},"width":1024,"sublayerTransform":[1,0,0,0,0,1,0,0,0,0,1,0,0,0,0,1],"contentsRect":{"y":0,"x":0,"width":1,"height":1},"opacity":1,"edgeAntialiasingMask":0,"height":768,"hidden":false,"anchorPoint":{"pointX":0.5,"pointY":0.5}},"texture":"218C388A157E683BB1CD1B62B2692166"},{"animations":[{"timeOffset":0,"beginTime":0,"repeatCount":0,"animations":[{"timeOffset":0,"from":{"scalar":1},"beginTime":0.22499999999999998,"repeatCount":0,"fillMode":"both","duration":0.82500000000000007,"autoreverses":false,"timingFunction":"EaseIn","property":"opacity","to":{"scalar":0}},{"timeOffset":0,"from":{"scalar":false},"beginTime":0,"repeatCount":0,"fillMode":"removed","property":"doubleSided","autoreverses":false,"duration":1.5,"to":{"scalar":false}},{"timeOffset":0,"timingFunctions":[{"timingFunction":"custom","timingControlPoint1y":0,"timingControlPoint2x":0.6983528733253479,"timingControlPoint1x":0.30636021494865417,"timingControlPoint2y":1},{"timingFunction":"custom","timingControlPoint1y":0,"timingControlPoint2x":0.69753515720367432,"timingControlPoint1x":0.29726776480674744,"timingControlPoint2y":1},{"timingFunction":"custom","timingControlPoint1y":0,"timingControlPoint2x":0.70256143808364868,"timingControlPoint1x":0.30822962522506714,"timingControlPoint2y":1},{"timingFunction":"custom","timingControlPoint1y":0,"timingControlPoint2x":0.69328594207763672,"timingControlPoint1x":0.29690060019493103,"timingControlPoint2y":1}],"beginTime":0,"values":[{"scalar":-0},{"scalar":0.10000000000000001},{"scalar":-1.6707963267948966},{"scalar":-1.5407963267948965},{"scalar":-1.5707963267948966}],"repeatCount":0,"fillMode":"removed","property":"transform.rotation.y","autoreverses":false,"duration":1.5,"keyTimes":[0,0.14999999999999999,0.55000000000000004,0.77500000000000002,1]},{"timeOffset":0,"from":{"scalar":-512},"beginTime":0,"repeatCount":0,"fillMode":"removed","property":"transform.translation.z","autoreverses":false,"duration":1.5,"to":{"scalar":-512}},{"timeOffset":0,"from":{"scalar":-512},"beginTime":0,"repeatCount":0,"fillMode":"removed","property":"anchorPointZ","autoreverses":false,"duration":1.5,"to":{"scalar":-512}}],"fillMode":"both","autoreverses":false,"duration":1.5}],"layers":[],"texturedRectangle":{"isBackgroundTexture":false,"singleTextureOpacity":1,"textureType":0,"textBaseline":0,"textXHeight":0,"isVerticalText":false},"initialState":{"affineTransform":[1,0,0,1,0,0],"masksToBounds":false,"rotation":0,"scale":1,"position":{"pointX":512,"pointY":384},"width":1024,"sublayerTransform":[1,0,0,0,0,1,0,0,0,0,1,0,0,0,0,1],"contentsRect":{"y":0,"x":0,"width":1,"height":1},"opacity":1,"edgeAntialiasingMask":0,"height":768,"hidden":false,"anchorPoint":{"pointX":0.5,"pointY":0.5}},"texture":"730F45CA9B52757583F432DB4F57BC3E"}]}]},"effects":[],"duration":1.5,"type":"transition","attributes":{"direction":12},"name":"apple:3D-cube","objectID":"0"}],"automaticPlay":false,"hyperlinks":[],"accessibility":[{"text":"pasted-image.tiff","targetRectangle":{"y":385.57037353515625,"x":371.70663452148438,"width":600.78125,"height":330.42962646484375}},{"text":"pasted-image.tiff","targetRectangle":{"y":613.63971914356614,"x":-0.80919802188873291,"width":117.125,"height":155.2908340327723}},{"text":"Newtonian Gravity ","targetRectangle":{"y":111.540358543396,"x":34.578115463256779,"width":296.97500000000008,"height":48}},{"text":"to ","targetRectangle":{"y":159.540358543396,"x":162.29311546325684,"width":41.545000000000016,"height":48}},{"text":"Einstein’s ","targetRectangle":{"y":207.540358543396,"x":107.20311546325684,"width":151.72500000000002,"height":48}},{"text":"General Relativity","targetRectangle":{"y":255.540358543396,"x":42.383115463256786,"width":272.26500000000004,"height":48}},{"text":"(1919)","targetRectangle":{"y":303.540358543396,"x":133.01561546325684,"width":91,"height":48}},{"text":"pasted-image.tiff","targetRectangle":{"y":99.118499755859375,"x":371.70662294261092,"width":600.79682721261634,"height":266.83578205496815}},{"text":"Classical ","targetRectangle":{"y":406.78515434265137,"x":112.10311546325684,"width":141.92499999999998,"height":48}},{"text":"Mechanics","targetRectangle":{"y":454.78515434265137,"x":96.195615463256829,"width":164.63999999999999,"height":48}},{"text":"to ","targetRectangle":{"y":502.78515434265137,"x":162.29311546325684,"width":41.545000000000016,"height":48}},{"text":"Quantum ","targetRectangle":{"y":550.78515434265137,"x":104.91061546325685,"width":156.31000000000003,"height":48}},{"text":"Mechanics ","targetRectangle":{"y":598.78515434265137,"x":96.195615463256843,"width":173.74000000000001,"height":48}},{"text":"(1905)","targetRectangle":{"y":646.78515434265137,"x":133.01561546325684,"width":91,"height":48}}],"baseLayer":{"animations":[],"initialState":{"affineTransform":[1,0,0,1,0,0],"masksToBounds":false,"rotation":0,"scale":1,"position":{"pointX":512,"pointY":384},"width":1024,"sublayerTransform":[1,0,0,0,0,1,0,0,0,0,1,0,0,0,0,1],"contentsRect":{"y":0,"x":0,"width":1,"height":1},"opacity":1,"edgeAntialiasingMask":251658240,"height":768,"hidden":false,"anchorPoint":{"pointX":0.5,"pointY":0.5}},"objectID":"0","layers":[{"animations":[],"initialState":{"affineTransform":[1,0,0,1,0,0],"masksToBounds":false,"rotation":0,"scale":1,"position":{"pointX":512,"pointY":384},"width":1024,"sublayerTransform":[1,0,0,0,0,1,0,0,0,0,1,-0.00049229876906403734,0,0,0,1],"contentsRect":{"y":0,"x":0,"width":1,"height":1},"opacity":1,"edgeAntialiasingMask":251658240,"height":768,"hidden":false,"anchorPoint":{"pointX":0.5,"pointY":0.5}},"layers":[{"animations":[],"layers":[],"texturedRectangle":{"isBackgroundTexture":false,"singleTextureOpacity":1,"textureType":0,"textBaseline":0,"textXHeight":0,"isVerticalText":false},"initialState":{"affineTransform":[1,0,0,1,0,0],"masksToBounds":false,"rotation":0,"scale":1,"position":{"pointX":512,"pointY":384},"width":1024,"sublayerTransform":[1,0,0,0,0,1,0,0,0,0,1,0,0,0,0,1],"contentsRect":{"y":0,"x":0,"width":1,"height":1},"opacity":1,"edgeAntialiasingMask":0,"height":768,"hidden":false,"anchorPoint":{"pointX":0.5,"pointY":0.5}},"texture":"730F45CA9B52757583F432DB4F57BC3E"}]}]}}]}